[{"model": "admin.logentry", "pk": 1, "fields": {"action_time": "2023-02-15T23:48:25.851Z", "user": 1, "content_type": 13, "object_id": "3", "object_repr": "Komisja szkoleniowa", "action_flag": 2, "change_message": "[{\"changed\": {\"fields\": [\"Groups\"]}}]"}}, {"model": "admin.logentry", "pk": 2, "fields": {"action_time": "2023-02-15T23:48:30.189Z", "user": 1, "content_type": 13, "object_id": "4", "object_repr": "Organizator Testow", "action_flag": 2, "change_message": "[{\"changed\": {\"fields\": [\"Groups\"]}}]"}}, {"model": "auth.permission", "pk": 1, "fields": {"name": "Can add log entry", "content_type": 1, "codename": "add_logentry"}}, {"model": "auth.permission", "pk": 2, "fields": {"name": "Can change log entry", "content_type": 1, "codename": "change_logentry"}}, {"model": "auth.permission", "pk": 3, "fields": {"name": "Can delete log entry", "content_type": 1, "codename": "delete_logentry"}}, {"model": "auth.permission", "pk": 4, "fields": {"name": "Can view log entry", "content_type": 1, "codename": "view_logentry"}}, {"model": "auth.permission", "pk": 5, "fields": {"name": "Can add permission", "content_type": 2, "codename": "add_permission"}}, {"model": "auth.permission", "pk": 6, "fields": {"name": "Can change permission", "content_type": 2, "codename": "change_permission"}}, {"model": "auth.permission", "pk": 7, "fields": {"name": "Can delete permission", "content_type": 2, "codename": "delete_permission"}}, {"model": "auth.permission", "pk": 8, "fields": {"name": "Can view permission", "content_type": 2, "codename": "view_permission"}}, {"model": "auth.permission", "pk": 9, "fields": {"name": "Can add group", "content_type": 3, "codename": "add_group"}}, {"model": "auth.permission", "pk": 10, "fields": {"name": "Can change group", "content_type": 3, "codename": "change_group"}}, {"model": "auth.permission", "pk": 11, "fields": {"name": "Can delete group", "content_type": 3, "codename": "delete_group"}}, {"model": "auth.permission", "pk": 12, "fields": {"name": "Can view group", "content_type": 3, "codename": "view_group"}}, {"model": "auth.permission", "pk": 13, "fields": {"name": "Can add content type", "content_type": 4, "codename": "add_contenttype"}}, {"model": "auth.permission", "pk": 14, "fields": {"name": "Can change content type", "content_type": 4, "codename": "change_contenttype"}}, {"model": "auth.permission", "pk": 15, "fields": {"name": "Can delete content type", "content_type": 4, "codename": "delete_contenttype"}}, {"model": "auth.permission", "pk": 16, "fields": {"name": "Can view content type", "content_type": 4, "codename": "view_contenttype"}}, {"model": "auth.permission", "pk": 17, "fields": {"name": "Can add session", "content_type": 5, "codename": "add_session"}}, {"model": "auth.permission", "pk": 18, "fields": {"name": "Can change session", "content_type": 5, "codename": "change_session"}}, {"model": "auth.permission", "pk": 19, "fields": {"name": "Can delete session", "content_type": 5, "codename": "delete_session"}}, {"model": "auth.permission", "pk": 20, "fields": {"name": "Can view session", "content_type": 5, "codename": "view_session"}}, {"model": "auth.permission", "pk": 21, "fields": {"name": "Can add all possible answers", "content_type": 6, "codename": "add_allpossibleanswers"}}, {"model": "auth.permission", "pk": 22, "fields": {"name": "Can change all possible answers", "content_type": 6, "codename": "change_allpossibleanswers"}}, {"model": "auth.permission", "pk": 23, "fields": {"name": "Can delete all possible answers", "content_type": 6, "codename": "delete_allpossibleanswers"}}, {"model": "auth.permission", "pk": 24, "fields": {"name": "Can view all possible answers", "content_type": 6, "codename": "view_allpossibleanswers"}}, {"model": "auth.permission", "pk": 25, "fields": {"name": "Can add all test", "content_type": 7, "codename": "add_alltest"}}, {"model": "auth.permission", "pk": 26, "fields": {"name": "Can change all test", "content_type": 7, "codename": "change_alltest"}}, {"model": "auth.permission", "pk": 27, "fields": {"name": "Can delete all test", "content_type": 7, "codename": "delete_alltest"}}, {"model": "auth.permission", "pk": 28, "fields": {"name": "Can view all test", "content_type": 7, "codename": "view_alltest"}}, {"model": "auth.permission", "pk": 29, "fields": {"name": "Can add correct answer", "content_type": 8, "codename": "add_correctanswer"}}, {"model": "auth.permission", "pk": 30, "fields": {"name": "Can change correct answer", "content_type": 8, "codename": "change_correctanswer"}}, {"model": "auth.permission", "pk": 31, "fields": {"name": "Can delete correct answer", "content_type": 8, "codename": "delete_correctanswer"}}, {"model": "auth.permission", "pk": 32, "fields": {"name": "Can view correct answer", "content_type": 8, "codename": "view_correctanswer"}}, {"model": "auth.permission", "pk": 33, "fields": {"name": "Can add possible answers", "content_type": 9, "codename": "add_possibleanswers"}}, {"model": "auth.permission", "pk": 34, "fields": {"name": "Can change possible answers", "content_type": 9, "codename": "change_possibleanswers"}}, {"model": "auth.permission", "pk": 35, "fields": {"name": "Can delete possible answers", "content_type": 9, "codename": "delete_possibleanswers"}}, {"model": "auth.permission", "pk": 36, "fields": {"name": "Can view possible answers", "content_type": 9, "codename": "view_possibleanswers"}}, {"model": "auth.permission", "pk": 37, "fields": {"name": "Can add questions", "content_type": 10, "codename": "add_questions"}}, {"model": "auth.permission", "pk": 38, "fields": {"name": "Can change questions", "content_type": 10, "codename": "change_questions"}}, {"model": "auth.permission", "pk": 39, "fields": {"name": "Can delete questions", "content_type": 10, "codename": "delete_questions"}}, {"model": "auth.permission", "pk": 40, "fields": {"name": "Can view questions", "content_type": 10, "codename": "view_questions"}}, {"model": "auth.permission", "pk": 41, "fields": {"name": "Can add question test", "content_type": 11, "codename": "add_questiontest"}}, {"model": "auth.permission", "pk": 42, "fields": {"name": "Can change question test", "content_type": 11, "codename": "change_questiontest"}}, {"model": "auth.permission", "pk": 43, "fields": {"name": "Can delete question test", "content_type": 11, "codename": "delete_questiontest"}}, {"model": "auth.permission", "pk": 44, "fields": {"name": "Can view question test", "content_type": 11, "codename": "view_questiontest"}}, {"model": "auth.permission", "pk": 45, "fields": {"name": "Can add league", "content_type": 12, "codename": "add_league"}}, {"model": "auth.permission", "pk": 46, "fields": {"name": "Can change league", "content_type": 12, "codename": "change_league"}}, {"model": "auth.permission", "pk": 47, "fields": {"name": "Can delete league", "content_type": 12, "codename": "delete_league"}}, {"model": "auth.permission", "pk": 48, "fields": {"name": "Can view league", "content_type": 12, "codename": "view_league"}}, {"model": "auth.permission", "pk": 49, "fields": {"name": "Can add user", "content_type": 13, "codename": "add_user"}}, {"model": "auth.permission", "pk": 50, "fields": {"name": "Can change user", "content_type": 13, "codename": "change_user"}}, {"model": "auth.permission", "pk": 51, "fields": {"name": "Can delete user", "content_type": 13, "codename": "delete_user"}}, {"model": "auth.permission", "pk": 52, "fields": {"name": "Can view user", "content_type": 13, "codename": "view_user"}}, {"model": "auth.permission", "pk": 53, "fields": {"name": "Can add organise test", "content_type": 14, "codename": "add_organisetest"}}, {"model": "auth.permission", "pk": 54, "fields": {"name": "Can change organise test", "content_type": 14, "codename": "change_organisetest"}}, {"model": "auth.permission", "pk": 55, "fields": {"name": "Can delete organise test", "content_type": 14, "codename": "delete_organisetest"}}, {"model": "auth.permission", "pk": 56, "fields": {"name": "Can view organise test", "content_type": 14, "codename": "view_organisetest"}}, {"model": "auth.permission", "pk": 57, "fields": {"name": "Can add user solving", "content_type": 15, "codename": "add_usersolving"}}, {"model": "auth.permission", "pk": 58, "fields": {"name": "Can change user solving", "content_type": 15, "codename": "change_usersolving"}}, {"model": "auth.permission", "pk": 59, "fields": {"name": "Can delete user solving", "content_type": 15, "codename": "delete_usersolving"}}, {"model": "auth.permission", "pk": 60, "fields": {"name": "Can view user solving", "content_type": 15, "codename": "view_usersolving"}}, {"model": "auth.permission", "pk": 61, "fields": {"name": "Can add user test result", "content_type": 16, "codename": "add_usertestresult"}}, {"model": "auth.permission", "pk": 62, "fields": {"name": "Can change user test result", "content_type": 16, "codename": "change_usertestresult"}}, {"model": "auth.permission", "pk": 63, "fields": {"name": "Can delete user test result", "content_type": 16, "codename": "delete_usertestresult"}}, {"model": "auth.permission", "pk": 64, "fields": {"name": "Can view user test result", "content_type": 16, "codename": "view_usertestresult"}}, {"model": "auth.group", "pk": 1, "fields": {"name": "Sędziowie", "permissions": [32, 44]}}, {"model": "auth.group", "pk": 2, "fields": {"name": "Komisja szkoleniowa", "permissions": [29, 30, 32, 33, 34, 35, 36, 37, 38, 39, 40, 41, 42, 43, 44]}}, {"model": "auth.group", "pk": 3, "fields": {"name": "Organizator", "permissions": [4, 10, 12, 5, 6, 7, 8, 21, 22, 23, 24, 25, 26, 27, 28, 29, 30, 31, 32, 33, 34, 35, 36, 37, 38, 39, 40, 41, 42, 43, 44]}}, {"model": "auth.group", "pk": 4, "fields": {"name": "admin", "permissions": [1, 2, 3, 4, 9, 10, 11, 12, 5, 6, 7, 8, 13, 14, 15, 16, 53, 54, 55, 56, 57, 58, 59, 60, 61, 62, 63, 64, 21, 22, 23, 24, 17, 18, 19, 20, 25, 26, 27, 28, 29, 30, 31, 32, 33, 34, 35, 36, 37, 38, 39, 40, 41, 42, 43, 44, 45, 46, 47, 48, 49, 50, 51, 52]}}, {"model": "contenttypes.contenttype", "pk": 1, "fields": {"app_label": "admin", "model": "logentry"}}, {"model": "contenttypes.contenttype", "pk": 2, "fields": {"app_label": "auth", "model": "permission"}}, {"model": "contenttypes.contenttype", "pk": 3, "fields": {"app_label": "auth", "model": "group"}}, {"model": "contenttypes.contenttype", "pk": 4, "fields": {"app_label": "contenttypes", "model": "contenttype"}}, {"model": "contenttypes.contenttype", "pk": 5, "fields": {"app_label": "sessions", "model": "session"}}, {"model": "contenttypes.contenttype", "pk": 6, "fields": {"app_label": "Question_manager", "model": "allpossibleanswers"}}, {"model": "contenttypes.contenttype", "pk": 7, "fields": {"app_label": "Test_manager", "model": "alltest"}}, {"model": "contenttypes.contenttype", "pk": 8, "fields": {"app_label": "Test_manager", "model": "correctanswer"}}, {"model": "contenttypes.contenttype", "pk": 9, "fields": {"app_label": "Test_manager", "model": "possibleanswers"}}, {"model": "contenttypes.contenttype", "pk": 10, "fields": {"app_label": "Test_manager", "model": "questions"}}, {"model": "contenttypes.contenttype", "pk": 11, "fields": {"app_label": "Test_manager", "model": "questiontest"}}, {"model": "contenttypes.contenttype", "pk": 12, "fields": {"app_label": "User_manager", "model": "league"}}, {"model": "contenttypes.contenttype", "pk": 13, "fields": {"app_label": "User_manager", "model": "user"}}, {"model": "contenttypes.contenttype", "pk": 14, "fields": {"app_label": "Organization_test", "model": "organisetest"}}, {"model": "contenttypes.contenttype", "pk": 15, "fields": {"app_label": "Organization_test", "model": "usersolving"}}, {"model": "contenttypes.contenttype", "pk": 16, "fields": {"app_label": "Organization_test", "model": "usertestresult"}}, {"model": "sessions.session", "pk": "m5o1azw2kqb7jvt3xaroxa3oqqwfb4h7", "fields": {"session_data": ".eJxVjDsOwyAQBe9CHSEtYD4p0-cMiM9ucBKBZOzKyt1jJBdJOzPv7cyHbS1-67j4ObMrA3b5ZTGkF9Yh8jPUR-Op1XWZIx8JP23n95bxfTvbv4MSehlrAqnAZWkgIQoLmshOFEmRPWhEIUhKYSdEl7TUxsrDiKgyKBLOsM8X7CI3xw:1pSRVP:CHw5T-eoSb6piEFki18byvvb2p2_4Mfq4A59XLePgC8", "expire_date": "2023-03-01T23:48:07.697Z"}}, {"model": "Question_manager.allpossibleanswers", "pk": 1, "fields": {"all_kind_answers": "B"}}, {"model": "Question_manager.allpossibleanswers", "pk": 2, "fields": {"all_kind_answers": "P"}}, {"model": "Question_manager.allpossibleanswers", "pk": 3, "fields": {"all_kind_answers": "S"}}, {"model": "Question_manager.allpossibleanswers", "pk": 4, "fields": {"all_kind_answers": "Br"}}, {"model": "Question_manager.allpossibleanswers", "pk": 5, "fields": {"all_kind_answers": "Z"}}, {"model": "Question_manager.allpossibleanswers", "pk": 6, "fields": {"all_kind_answers": "G"}}, {"model": "Question_manager.allpossibleanswers", "pk": 7, "fields": {"all_kind_answers": "J"}}, {"model": "Question_manager.allpossibleanswers", "pk": 8, "fields": {"all_kind_answers": "Rb"}}, {"model": "Question_manager.allpossibleanswers", "pk": 9, "fields": {"all_kind_answers": "K"}}, {"model": "Question_manager.allpossibleanswers", "pk": 10, "fields": {"all_kind_answers": "R"}}, {"model": "Question_manager.allpossibleanswers", "pk": 11, "fields": {"all_kind_answers": "W"}}, {"model": "Question_manager.allpossibleanswers", "pk": 12, "fields": {"all_kind_answers": "+"}}, {"model": "Question_manager.allpossibleanswers", "pk": 13, "fields": {"all_kind_answers": "+"}}, {"model": "Question_manager.allpossibleanswers", "pk": 14, "fields": {"all_kind_answers": "+"}}, {"model": "Question_manager.allpossibleanswers", "pk": 15, "fields": {"all_kind_answers": "++"}}, {"model": "Question_manager.allpossibleanswers", "pk": 16, "fields": {"all_kind_answers": "++"}}, {"model": "Question_manager.allpossibleanswers", "pk": 17, "fields": {"all_kind_answers": "++"}}, {"model": "Question_manager.allpossibleanswers", "pk": 18, "fields": {"all_kind_answers": "TAK"}}, {"model": "Question_manager.allpossibleanswers", "pk": 19, "fields": {"all_kind_answers": "NIE"}}, {"model": "Question_manager.allpossibleanswers", "pk": 20, "fields": {"all_kind_answers": "A"}}, {"model": "Question_manager.allpossibleanswers", "pk": 21, "fields": {"all_kind_answers": "B"}},{"model": "Question_manager.allpossibleanswers", "pk": 22, "fields": {"all_kind_answers": "C"}}, {"model": "Question_manager.allpossibleanswers", "pk": 23, "fields": {"all_kind_answers": "D"}}, {"model": "Question_manager.allpossibleanswers", "pk": 24, "fields": {"all_kind_answers": "E"}}, {"model": "Question_manager.allpossibleanswers", "pk": 25, "fields": {"all_kind_answers": "F"}}, {"model": "Question_manager.allpossibleanswers", "pk": 26, "fields": {"all_kind_answers": "G"}} ,{"model": "Test_manager.questions", "pk": 1, "fields": {"add_question": "Gdy piłka była w grze, zawodnik zachował się niesportowo wobec przeciwnika na polu\r\ngry. Po przerwaniu gry i zastosowaniu kary napomnienia, sędzia wznowił ją rzutem\r\nwolnym pośrednim. Czy sędzia podjął prawidłową decyzję, jeżeli przewinienie polegało na\r\nsłownym prowokowaniu przeciwnika?", "for_league": 1, "added_by": 1, "added_date": "2023-02-15T23:52:05.935Z", "modify_date": "2023-02-15T23:52:05.935Z", "slug": "gdy-pika-bya-w-grze-zawodnik-zachowa-sie-niesp-1676505125"}}, {"model": "Test_manager.questions", "pk": 2, "fields": {"add_question": "Czy zawodnikom rezerwowym może towarzyszyć w rozgrzewce (w czasie gry) masażysta\r\ntej drużyny, jeśli został wpisany do protokołu?", "for_league": 1, "added_by": 1, "added_date": "2023-02-16T00:01:15.721Z", "modify_date": "2023-02-16T00:01:15.721Z", "slug": "czy-zawodnikom-rezerwowym-moze-towarzyszyc-w-rozgr-1676505675"}}, {"model": "Test_manager.questions", "pk": 3, "fields": {"add_question": "Czy podczas wykonywania rzutów z punktu karnego możliwa jest wymiana zawodnika z\r\npola (nie bramkarza), który doznał kontuzji, a jego drużyna nie wykorzystała jeszcze limitu\r\nwymian?", "for_league": 2, "added_by": 1, "added_date": "2023-02-16T00:01:33.116Z", "modify_date": "2023-02-16T00:01:33.116Z", "slug": "czy-podczas-wykonywania-rzutow-z-punktu-karnego-mo-1676505693"}}, {"model": "Test_manager.questions", "pk": 4, "fields": {"add_question": "Czy sędziemu wolno zakończyć zawody, jeżeli podczas wykonywania rzutów z punktu\r\nkarnego jedna z drużyn zostanie zredukowana do mniej niż siedmiu zawodników?", "for_league": 3, "added_by": 1, "added_date": "2023-02-16T00:01:50.438Z", "modify_date": "2023-02-16T00:01:50.438Z", "slug": "czy-sedziemu-wolno-zakonczyc-zawody-jezeli-podcza-1676505710"}}, {"model": "Test_manager.questions", "pk": 5, "fields": {"add_question": "Gdy piłka wyszła poza linię boczną trener drużyny przytrzymał piłkę, a następnie odrzucił\r\nją w bok, gdy wrzut miał wykonać zawodnik jego drużyny. Czy sędzia postąpił prawidłowo\r\nudzielając trenerowi napomnienia?", "for_league": 1, "added_by": 1, "added_date": "2023-02-16T00:02:02.245Z", "modify_date": "2023-02-16T00:02:02.245Z", "slug": "gdy-pika-wysza-poza-linie-boczna-trener-druzyny-1676505722"}}, {"model": "Test_manager.questions", "pk": 6, "fields": {"add_question": "Czy tylko zawodnicy drużyny przeciwnej muszą być ustawieni 4 metry od piłki w\r\nmomencie wykonania rzutu sędziowskiego?", "for_league": 6, "added_by": 1, "added_date": "2023-02-16T00:02:17.625Z", "modify_date": "2023-02-16T00:02:17.625Z", "slug": "czy-tylko-zawodnicy-druzyny-przeciwnej-musza-byc-u-1676505737"}}, {"model": "Test_manager.questions", "pk": 7, "fields": {"add_question": "W czasie gry po zagraniu piłki przez napastnika, piłka przypadkowo odbiła się od nogi\r\nsędziego, a następnie wpadła bezpośrednio do bramki. Czy gra zostanie wznowiona\r\nrzutem sędziowskim?", "for_league": 6, "added_by": 1, "added_date": "2023-02-16T00:02:36.462Z", "modify_date": "2023-02-16T00:02:36.462Z", "slug": "w-czasie-gry-po-zagraniu-piki-przez-napastnika-p-1676505756"}}, {"model": "Test_manager.questions", "pk": 8, "fields": {"add_question": "Czy popełnienie poważnego rażącego faulu jest zawsze karane wykluczeniem, nawet jeśli\r\nsędzia zastosował korzyść, po której drużyna przeciwna zdobyła bramkę?", "for_league": 4, "added_by": 1, "added_date": "2023-02-16T00:02:51.210Z", "modify_date": "2023-02-16T00:02:51.210Z", "slug": "czy-popenienie-powaznego-razacego-faulu-jest-zaws-1676505771"}}, {"model": "Test_manager.questions", "pk": 9, "fields": {"add_question": "Po gwizdku sędziego, rzut karny skutecznie wykonał inny zawodnik niż pierwotnie\r\nzidentyfikowany. Podaj decyzję sędziego.", "for_league": 6, "added_by": 1, "added_date": "2023-02-16T00:03:54.965Z", "modify_date": "2023-02-16T00:03:54.965Z", "slug": "po-gwizdku-sedziego-rzut-karny-skutecznie-wykona-1676505834"}}, {"model": "Test_manager.questions", "pk": 10, "fields": {"add_question": "Zawodnik powrócił na pole gry bez zgody sędziego, a następnie sfaulował przeciwnika,\r\nprzerywając tym samym korzystną akcję drużyny przeciwnej. Podaj decyzję sędziego", "for_league": 6, "added_by": 1, "added_date": "2023-02-16T00:06:21.326Z", "modify_date": "2023-02-16T00:06:21.326Z", "slug": "zawodnik-powroci-na-pole-gry-bez-zgody-sedziego-1676505981"}}, {"model": "Test_manager.questions", "pk": 11, "fields": {"add_question": "W czasie gdy piłka była w grze, bramkarz brutalnie uderzył swojego przeciwnika\r\nznajdującego się wewnątrz bramki. Podaj decyzję sędziego.", "for_league": 2, "added_by": 1, "added_date": "2023-02-16T00:06:37.702Z", "modify_date": "2023-02-16T00:06:37.702Z", "slug": "w-czasie-gdy-pika-bya-w-grze-bramkarz-brutalnie-1676505997"}}, {"model": "Test_manager.questions", "pk": 12, "fields": {"add_question": "Zawodnik rozpoczynający grę zauważył, że bramkarz drużyny przeciwnej stoi na linii pola\r\nkarnego. Natychmiast po gwizdku sędziego kopnął mocno piłkę, tak że wpadła ona\r\nbezpośrednio do bramki przeciwnika. Podaj decyzję sędziego.", "for_league": 2, "added_by": 1, "added_date": "2023-02-16T00:07:13.015Z", "modify_date": "2023-02-16T00:07:13.015Z", "slug": "zawodnik-rozpoczynajacy-gre-zauwazy-ze-bramkarz-1676506033"}}, {"model": "Test_manager.questions", "pk": 13, "fields": {"add_question": "Masażysta drużyny gości wszedł we własne pole karne, gdy zauważył, że nikt inny nie\r\nbędzie w stanie zapobiec utracie bramki i wybił zmierzającą do pustej bramki. Podaj\r\ndecyzję sędziego.", "for_league": 6, "added_by": 1, "added_date": "2023-02-16T00:07:34.530Z", "modify_date": "2023-02-16T00:07:34.530Z", "slug": "masazysta-druzyny-gosci-wszed-we-wasne-pole-karn-1676506054"}}, {"model": "Test_manager.questions", "pk": 14, "fields": {"add_question": "Mający już żółtą kartkę na swoim koncie zawodnik zgubił w czasie gry ochraniacz i zanim\r\nsędzia zdążył zareagować, bezpośrednim strzałem zdobył bramkę. Podaj decyzję sędziego", "for_league": 6, "added_by": 1, "added_date": "2023-02-16T00:07:50.631Z", "modify_date": "2023-02-16T00:07:50.631Z", "slug": "majacy-juz-zota-kartke-na-swoim-koncie-zawodnik-z-1676506070"}}, {"model": "Test_manager.questions", "pk": 15, "fields": {"add_question": "Obrońca popełnił przewinienie w stosunku do będącego przed polem karnym sędziego,\r\nkrzycząc „Ile ci zapłacili za tego karnego?!”, w sytuacji, gdy przeciwnicy mieli realną szansę\r\nna zdobycie bramki. Podaj decyzję sędziego.", "for_league": 1, "added_by": 1, "added_date": "2023-02-16T00:08:19.992Z", "modify_date": "2023-02-16T00:08:19.992Z", "slug": "obronca-popeni-przewinienie-w-stosunku-do-bedace-1676506099"}}, {"model": "Test_manager.questions", "pk": 16, "fields": {"add_question": "Wykonawca rzutu rożnego potknął się w czasie dobiegania do piłki, przez co upadając\r\nzagrał piłkę kolanem. Piłka wtoczyła się w pole gry, gdzie od razu przejął ją współpartner\r\nwykonawcy i dośrodkował piłkę w pole karne przeciwników. Podaj decyzję sędziego", "for_league": 2, "added_by": 1, "added_date": "2023-02-16T00:08:42.793Z", "modify_date": "2023-02-16T00:08:42.793Z", "slug": "wykonawca-rzutu-roznego-potkna-sie-w-czasie-dobie-1676506122"}}, {"model": "Test_manager.questions", "pk": 17, "fields": {"add_question": "Zawodnicy drużyny broniącej w wyniku akcji znaleźli się we własnej bramce. Jeden z tych\r\nzawodników uderzył z dużą siłą współpartnera w twarz. W tym czasie drużyna przeciwna\r\nposiadała korzystną akcję. Podaj decyzję sędziego.", "for_league": 1, "added_by": 1, "added_date": "2023-02-16T00:09:07.307Z", "modify_date": "2023-02-16T00:09:07.307Z", "slug": "zawodnicy-druzyny-broniacej-w-wyniku-akcji-znalezl-1676506147"}}, {"model": "Test_manager.questions", "pk": 18, "fields": {"add_question": "Napastnik będący na 18. metrze od bramki przeciwników znajduje się w sytuacji sam na\r\nsam z bramkarzem. Będący za nim obrońca wykonuje wślizg, usiłując wybić piłkę, jednak\r\njej nie sięga, natomiast nieostrożnie podstawia nogę napastnikowi. Podaj decyzję\r\nsędziego.", "for_league": 6, "added_by": 1, "added_date": "2023-02-16T00:09:34.527Z", "modify_date": "2023-02-16T00:09:34.527Z", "slug": "napastnik-bedacy-na-18-metrze-od-bramki-przeciwni-1676506174"}}, {"model": "Test_manager.questions", "pk": 19, "fields": {"add_question": "Zawodnik drużyny broniącej, we własnym polu karnym rozmyślnie zatrzymał piłkę ręką,\r\npozbawiając tym samym przeciwnika realnej szansy na zdobycie bramki. Podaj decyzję\r\nsędziego.", "for_league": 6, "added_by": 1, "added_date": "2023-02-16T00:09:54.883Z", "modify_date": "2023-02-16T00:09:54.883Z", "slug": "zawodnik-druzyny-broniacej-we-wasnym-polu-karnym-1676506194"}}, {"model": "Test_manager.questions", "pk": 20, "fields": {"add_question": "Napastnik oddał strzał na bramkę, a stojący na linii pola karnego obrońca, aby ten strzał\r\nobronić, świadomie i celowo wybił piłkę nogą w bok. Ta jednak trafiła do innego\r\nnapastnika będącego w momencie strzału na pozycji spalonej, który wykonał skuteczną\r\ndobitkę i zdobył bramkę. Podaj decyzję sędziego.", "for_league": 5, "added_by": 1, "added_date": "2023-02-16T00:10:10.261Z", "modify_date": "2023-02-16T00:10:10.261Z", "slug": "napastnik-odda-strza-na-bramke-a-stojacy-na-lin-1676506210"}}, {"model": "Test_manager.questions", "pk": 21, "fields": {"add_question": "Wewnątrz własnego pola karnego bramkarz zagrał piłkę ręka po rozmyślnym podaniu od\r\nwspółpartnera, co przerwało przeciwnikowi możliwość przejęcia piłki w sytuacji\r\nkorzystnej. Podaj decyzję sędziego.", "for_league": 3, "added_by": 1, "added_date": "2023-02-16T00:44:16.249Z", "modify_date": "2023-02-16T00:44:16.249Z", "slug": "wewnatrz-wasnego-pola-karnego-bramkarz-zagra-pi-1676508256"}}, {"model": "Test_manager.possibleanswers", "pk": 1, "fields": {"question": 1, "question_possible_answers": 17}}, {"model": "Test_manager.possibleanswers", "pk": 2, "fields": {"question": 1, "question_possible_answers": 18}}, {"model": "Test_manager.possibleanswers", "pk": 3, "fields": {"question": 2, "question_possible_answers": 17}}, {"model": "Test_manager.possibleanswers", "pk": 4, "fields": {"question": 2, "question_possible_answers": 18}}, {"model": "Test_manager.possibleanswers", "pk": 5, "fields": {"question": 3, "question_possible_answers": 17}}, {"model": "Test_manager.possibleanswers", "pk": 6, "fields": {"question": 3, "question_possible_answers": 18}}, {"model": "Test_manager.possibleanswers", "pk": 7, "fields": {"question": 4, "question_possible_answers": 17}}, {"model": "Test_manager.possibleanswers", "pk": 8, "fields": {"question": 4, "question_possible_answers": 18}}, {"model": "Test_manager.possibleanswers", "pk": 9, "fields": {"question": 5, "question_possible_answers": 17}}, {"model": "Test_manager.possibleanswers", "pk": 10, "fields": {"question": 5, "question_possible_answers": 18}}, {"model": "Test_manager.possibleanswers", "pk": 11, "fields": {"question": 6, "question_possible_answers": 17}}, {"model": "Test_manager.possibleanswers", "pk": 12, "fields": {"question": 6, "question_possible_answers": 18}}, {"model": "Test_manager.possibleanswers", "pk": 13, "fields": {"question": 7, "question_possible_answers": 17}}, {"model": "Test_manager.possibleanswers", "pk": 14, "fields": {"question": 7, "question_possible_answers": 18}}, {"model": "Test_manager.possibleanswers", "pk": 15, "fields": {"question": 8, "question_possible_answers": 17}}, {"model": "Test_manager.possibleanswers", "pk": 16, "fields": {"question": 8, "question_possible_answers": 18}}, {"model": "Test_manager.possibleanswers", "pk": 17, "fields": {"question": 9, "question_possible_answers": 1}}, {"model": "Test_manager.possibleanswers", "pk": 18, "fields": {"question": 9, "question_possible_answers": 2}}, {"model": "Test_manager.possibleanswers", "pk": 19, "fields": {"question": 9, "question_possible_answers": 3}}, {"model": "Test_manager.possibleanswers", "pk": 20, "fields": {"question": 9, "question_possible_answers": 4}}, {"model": "Test_manager.possibleanswers", "pk": 21, "fields": {"question": 9, "question_possible_answers": 5}}, {"model": "Test_manager.possibleanswers", "pk": 22, "fields": {"question": 9, "question_possible_answers": 6}}, {"model": "Test_manager.possibleanswers", "pk": 23, "fields": {"question": 9, "question_possible_answers": 7}}, {"model": "Test_manager.possibleanswers", "pk": 24, "fields": {"question": 9, "question_possible_answers": 8}}, {"model": "Test_manager.possibleanswers", "pk": 25, "fields": {"question": 9, "question_possible_answers": 9}}, {"model": "Test_manager.possibleanswers", "pk": 26, "fields": {"question": 9, "question_possible_answers": 10}}, {"model": "Test_manager.possibleanswers", "pk": 27, "fields": {"question": 9, "question_possible_answers": 11}}, {"model": "Test_manager.possibleanswers", "pk": 28, "fields": {"question": 9, "question_possible_answers": 12}}, {"model": "Test_manager.possibleanswers", "pk": 29, "fields": {"question": 9, "question_possible_answers": 13}}, {"model": "Test_manager.possibleanswers", "pk": 30, "fields": {"question": 9, "question_possible_answers": 14}}, {"model": "Test_manager.possibleanswers", "pk": 31, "fields": {"question": 9, "question_possible_answers": 15}}, {"model": "Test_manager.possibleanswers", "pk": 32, "fields": {"question": 9, "question_possible_answers": 16}}, {"model": "Test_manager.possibleanswers", "pk": 33, "fields": {"question": 10, "question_possible_answers": 1}}, {"model": "Test_manager.possibleanswers", "pk": 34, "fields": {"question": 10, "question_possible_answers": 2}}, {"model": "Test_manager.possibleanswers", "pk": 35, "fields": {"question": 10, "question_possible_answers": 3}}, {"model": "Test_manager.possibleanswers", "pk": 36, "fields": {"question": 10, "question_possible_answers": 4}}, {"model": "Test_manager.possibleanswers", "pk": 37, "fields": {"question": 10, "question_possible_answers": 5}}, {"model": "Test_manager.possibleanswers", "pk": 38, "fields": {"question": 10, "question_possible_answers": 6}}, {"model": "Test_manager.possibleanswers", "pk": 39, "fields": {"question": 10, "question_possible_answers": 7}}, {"model": "Test_manager.possibleanswers", "pk": 40, "fields": {"question": 10, "question_possible_answers": 8}}, {"model": "Test_manager.possibleanswers", "pk": 41, "fields": {"question": 10, "question_possible_answers": 9}}, {"model": "Test_manager.possibleanswers", "pk": 42, "fields": {"question": 10, "question_possible_answers": 10}}, {"model": "Test_manager.possibleanswers", "pk": 43, "fields": {"question": 10, "question_possible_answers": 11}}, {"model": "Test_manager.possibleanswers", "pk": 44, "fields": {"question": 10, "question_possible_answers": 12}}, {"model": "Test_manager.possibleanswers", "pk": 45, "fields": {"question": 10, "question_possible_answers": 13}}, {"model": "Test_manager.possibleanswers", "pk": 46, "fields": {"question": 10, "question_possible_answers": 14}}, {"model": "Test_manager.possibleanswers", "pk": 47, "fields": {"question": 10, "question_possible_answers": 15}}, {"model": "Test_manager.possibleanswers", "pk": 48, "fields": {"question": 10, "question_possible_answers": 16}}, {"model": "Test_manager.possibleanswers", "pk": 49, "fields": {"question": 11, "question_possible_answers": 1}}, {"model": "Test_manager.possibleanswers", "pk": 50, "fields": {"question": 11, "question_possible_answers": 2}}, {"model": "Test_manager.possibleanswers", "pk": 51, "fields": {"question": 11, "question_possible_answers": 3}}, {"model": "Test_manager.possibleanswers", "pk": 52, "fields": {"question": 11, "question_possible_answers": 4}}, {"model": "Test_manager.possibleanswers", "pk": 53, "fields": {"question": 11, "question_possible_answers": 5}}, {"model": "Test_manager.possibleanswers", "pk": 54, "fields": {"question": 11, "question_possible_answers": 6}}, {"model": "Test_manager.possibleanswers", "pk": 55, "fields": {"question": 11, "question_possible_answers": 7}}, {"model": "Test_manager.possibleanswers", "pk": 56, "fields": {"question": 11, "question_possible_answers": 8}}, {"model": "Test_manager.possibleanswers", "pk": 57, "fields": {"question": 11, "question_possible_answers": 9}}, {"model": "Test_manager.possibleanswers", "pk": 58, "fields": {"question": 11, "question_possible_answers": 10}}, {"model": "Test_manager.possibleanswers", "pk": 59, "fields": {"question": 11, "question_possible_answers": 11}}, {"model": "Test_manager.possibleanswers", "pk": 60, "fields": {"question": 11, "question_possible_answers": 12}}, {"model": "Test_manager.possibleanswers", "pk": 61, "fields": {"question": 11, "question_possible_answers": 13}}, {"model": "Test_manager.possibleanswers", "pk": 62, "fields": {"question": 11, "question_possible_answers": 14}}, {"model": "Test_manager.possibleanswers", "pk": 63, "fields": {"question": 11, "question_possible_answers": 15}}, {"model": "Test_manager.possibleanswers", "pk": 64, "fields": {"question": 11, "question_possible_answers": 16}}, {"model": "Test_manager.possibleanswers", "pk": 65, "fields": {"question": 12, "question_possible_answers": 1}}, {"model": "Test_manager.possibleanswers", "pk": 66, "fields": {"question": 12, "question_possible_answers": 2}}, {"model": "Test_manager.possibleanswers", "pk": 67, "fields": {"question": 12, "question_possible_answers": 3}}, {"model": "Test_manager.possibleanswers", "pk": 68, "fields": {"question": 12, "question_possible_answers": 4}}, {"model": "Test_manager.possibleanswers", "pk": 69, "fields": {"question": 12, "question_possible_answers": 5}}, {"model": "Test_manager.possibleanswers", "pk": 70, "fields": {"question": 12, "question_possible_answers": 6}}, {"model": "Test_manager.possibleanswers", "pk": 71, "fields": {"question": 12, "question_possible_answers": 7}}, {"model": "Test_manager.possibleanswers", "pk": 72, "fields": {"question": 12, "question_possible_answers": 8}}, {"model": "Test_manager.possibleanswers", "pk": 73, "fields": {"question": 12, "question_possible_answers": 9}}, {"model": "Test_manager.possibleanswers", "pk": 74, "fields": {"question": 12, "question_possible_answers": 10}}, {"model": "Test_manager.possibleanswers", "pk": 75, "fields": {"question": 12, "question_possible_answers": 11}}, {"model": "Test_manager.possibleanswers", "pk": 76, "fields": {"question": 12, "question_possible_answers": 12}}, {"model": "Test_manager.possibleanswers", "pk": 77, "fields": {"question": 12, "question_possible_answers": 13}}, {"model": "Test_manager.possibleanswers", "pk": 78, "fields": {"question": 12, "question_possible_answers": 14}}, {"model": "Test_manager.possibleanswers", "pk": 79, "fields": {"question": 12, "question_possible_answers": 15}}, {"model": "Test_manager.possibleanswers", "pk": 80, "fields": {"question": 12, "question_possible_answers": 16}}, {"model": "Test_manager.possibleanswers", "pk": 81, "fields": {"question": 13, "question_possible_answers": 1}}, {"model": "Test_manager.possibleanswers", "pk": 82, "fields": {"question": 13, "question_possible_answers": 2}}, {"model": "Test_manager.possibleanswers", "pk": 83, "fields": {"question": 13, "question_possible_answers": 3}}, {"model": "Test_manager.possibleanswers", "pk": 84, "fields": {"question": 13, "question_possible_answers": 4}}, {"model": "Test_manager.possibleanswers", "pk": 85, "fields": {"question": 13, "question_possible_answers": 5}}, {"model": "Test_manager.possibleanswers", "pk": 86, "fields": {"question": 13, "question_possible_answers": 6}}, {"model": "Test_manager.possibleanswers", "pk": 87, "fields": {"question": 13, "question_possible_answers": 7}}, {"model": "Test_manager.possibleanswers", "pk": 88, "fields": {"question": 13, "question_possible_answers": 8}}, {"model": "Test_manager.possibleanswers", "pk": 89, "fields": {"question": 13, "question_possible_answers": 9}}, {"model": "Test_manager.possibleanswers", "pk": 90, "fields": {"question": 13, "question_possible_answers": 10}}, {"model": "Test_manager.possibleanswers", "pk": 91, "fields": {"question": 13, "question_possible_answers": 11}}, {"model": "Test_manager.possibleanswers", "pk": 92, "fields": {"question": 13, "question_possible_answers": 12}}, {"model": "Test_manager.possibleanswers", "pk": 93, "fields": {"question": 13, "question_possible_answers": 13}}, {"model": "Test_manager.possibleanswers", "pk": 94, "fields": {"question": 13, "question_possible_answers": 14}}, {"model": "Test_manager.possibleanswers", "pk": 95, "fields": {"question": 13, "question_possible_answers": 15}}, {"model": "Test_manager.possibleanswers", "pk": 96, "fields": {"question": 13, "question_possible_answers": 16}}, {"model": "Test_manager.possibleanswers", "pk": 97, "fields": {"question": 14, "question_possible_answers": 1}}, {"model": "Test_manager.possibleanswers", "pk": 98, "fields": {"question": 14, "question_possible_answers": 2}}, {"model": "Test_manager.possibleanswers", "pk": 99, "fields": {"question": 14, "question_possible_answers": 3}}, {"model": "Test_manager.possibleanswers", "pk": 100, "fields": {"question": 14, "question_possible_answers": 4}}, {"model": "Test_manager.possibleanswers", "pk": 101, "fields": {"question": 14, "question_possible_answers": 5}}, {"model": "Test_manager.possibleanswers", "pk": 102, "fields": {"question": 14, "question_possible_answers": 6}}, {"model": "Test_manager.possibleanswers", "pk": 103, "fields": {"question": 14, "question_possible_answers": 7}}, {"model": "Test_manager.possibleanswers", "pk": 104, "fields": {"question": 14, "question_possible_answers": 8}}, {"model": "Test_manager.possibleanswers", "pk": 105, "fields": {"question": 14, "question_possible_answers": 9}}, {"model": "Test_manager.possibleanswers", "pk": 106, "fields": {"question": 14, "question_possible_answers": 10}}, {"model": "Test_manager.possibleanswers", "pk": 107, "fields": {"question": 14, "question_possible_answers": 11}}, {"model": "Test_manager.possibleanswers", "pk": 108, "fields": {"question": 14, "question_possible_answers": 12}}, {"model": "Test_manager.possibleanswers", "pk": 109, "fields": {"question": 14, "question_possible_answers": 13}}, {"model": "Test_manager.possibleanswers", "pk": 110, "fields": {"question": 14, "question_possible_answers": 14}}, {"model": "Test_manager.possibleanswers", "pk": 111, "fields": {"question": 14, "question_possible_answers": 15}}, {"model": "Test_manager.possibleanswers", "pk": 112, "fields": {"question": 14, "question_possible_answers": 16}}, {"model": "Test_manager.possibleanswers", "pk": 113, "fields": {"question": 15, "question_possible_answers": 1}}, {"model": "Test_manager.possibleanswers", "pk": 114, "fields": {"question": 15, "question_possible_answers": 2}}, {"model": "Test_manager.possibleanswers", "pk": 115, "fields": {"question": 15, "question_possible_answers": 3}}, {"model": "Test_manager.possibleanswers", "pk": 116, "fields": {"question": 15, "question_possible_answers": 4}}, {"model": "Test_manager.possibleanswers", "pk": 117, "fields": {"question": 15, "question_possible_answers": 5}}, {"model": "Test_manager.possibleanswers", "pk": 118, "fields": {"question": 15, "question_possible_answers": 6}}, {"model": "Test_manager.possibleanswers", "pk": 119, "fields": {"question": 15, "question_possible_answers": 7}}, {"model": "Test_manager.possibleanswers", "pk": 120, "fields": {"question": 15, "question_possible_answers": 8}}, {"model": "Test_manager.possibleanswers", "pk": 121, "fields": {"question": 15, "question_possible_answers": 9}}, {"model": "Test_manager.possibleanswers", "pk": 122, "fields": {"question": 15, "question_possible_answers": 10}}, {"model": "Test_manager.possibleanswers", "pk": 123, "fields": {"question": 15, "question_possible_answers": 11}}, {"model": "Test_manager.possibleanswers", "pk": 124, "fields": {"question": 15, "question_possible_answers": 12}}, {"model": "Test_manager.possibleanswers", "pk": 125, "fields": {"question": 15, "question_possible_answers": 13}}, {"model": "Test_manager.possibleanswers", "pk": 126, "fields": {"question": 15, "question_possible_answers": 14}}, {"model": "Test_manager.possibleanswers", "pk": 127, "fields": {"question": 15, "question_possible_answers": 15}}, {"model": "Test_manager.possibleanswers", "pk": 128, "fields": {"question": 15, "question_possible_answers": 16}}, {"model": "Test_manager.possibleanswers", "pk": 129, "fields": {"question": 16, "question_possible_answers": 1}}, {"model": "Test_manager.possibleanswers", "pk": 130, "fields": {"question": 16, "question_possible_answers": 2}}, {"model": "Test_manager.possibleanswers", "pk": 131, "fields": {"question": 16, "question_possible_answers": 3}}, {"model": "Test_manager.possibleanswers", "pk": 132, "fields": {"question": 16, "question_possible_answers": 4}}, {"model": "Test_manager.possibleanswers", "pk": 133, "fields": {"question": 16, "question_possible_answers": 5}}, {"model": "Test_manager.possibleanswers", "pk": 134, "fields": {"question": 16, "question_possible_answers": 6}}, {"model": "Test_manager.possibleanswers", "pk": 135, "fields": {"question": 16, "question_possible_answers": 7}}, {"model": "Test_manager.possibleanswers", "pk": 136, "fields": {"question": 16, "question_possible_answers": 8}}, {"model": "Test_manager.possibleanswers", "pk": 137, "fields": {"question": 16, "question_possible_answers": 9}}, {"model": "Test_manager.possibleanswers", "pk": 138, "fields": {"question": 16, "question_possible_answers": 10}}, {"model": "Test_manager.possibleanswers", "pk": 139, "fields": {"question": 16, "question_possible_answers": 11}}, {"model": "Test_manager.possibleanswers", "pk": 140, "fields": {"question": 16, "question_possible_answers": 12}}, {"model": "Test_manager.possibleanswers", "pk": 141, "fields": {"question": 16, "question_possible_answers": 13}}, {"model": "Test_manager.possibleanswers", "pk": 142, "fields": {"question": 16, "question_possible_answers": 14}}, {"model": "Test_manager.possibleanswers", "pk": 143, "fields": {"question": 16, "question_possible_answers": 15}}, {"model": "Test_manager.possibleanswers", "pk": 144, "fields": {"question": 16, "question_possible_answers": 16}}, {"model": "Test_manager.possibleanswers", "pk": 145, "fields": {"question": 17, "question_possible_answers": 1}}, {"model": "Test_manager.possibleanswers", "pk": 146, "fields": {"question": 17, "question_possible_answers": 2}}, {"model": "Test_manager.possibleanswers", "pk": 147, "fields": {"question": 17, "question_possible_answers": 3}}, {"model": "Test_manager.possibleanswers", "pk": 148, "fields": {"question": 17, "question_possible_answers": 4}}, {"model": "Test_manager.possibleanswers", "pk": 149, "fields": {"question": 17, "question_possible_answers": 5}}, {"model": "Test_manager.possibleanswers", "pk": 150, "fields": {"question": 17, "question_possible_answers": 6}}, {"model": "Test_manager.possibleanswers", "pk": 151, "fields": {"question": 17, "question_possible_answers": 7}}, {"model": "Test_manager.possibleanswers", "pk": 152, "fields": {"question": 17, "question_possible_answers": 8}}, {"model": "Test_manager.possibleanswers", "pk": 153, "fields": {"question": 17, "question_possible_answers": 9}}, {"model": "Test_manager.possibleanswers", "pk": 154, "fields": {"question": 17, "question_possible_answers": 10}}, {"model": "Test_manager.possibleanswers", "pk": 155, "fields": {"question": 17, "question_possible_answers": 11}}, {"model": "Test_manager.possibleanswers", "pk": 156, "fields": {"question": 17, "question_possible_answers": 12}}, {"model": "Test_manager.possibleanswers", "pk": 157, "fields": {"question": 17, "question_possible_answers": 13}}, {"model": "Test_manager.possibleanswers", "pk": 158, "fields": {"question": 17, "question_possible_answers": 14}}, {"model": "Test_manager.possibleanswers", "pk": 159, "fields": {"question": 17, "question_possible_answers": 15}}, {"model": "Test_manager.possibleanswers", "pk": 160, "fields": {"question": 17, "question_possible_answers": 16}}, {"model": "Test_manager.possibleanswers", "pk": 161, "fields": {"question": 18, "question_possible_answers": 1}}, {"model": "Test_manager.possibleanswers", "pk": 162, "fields": {"question": 18, "question_possible_answers": 2}}, {"model": "Test_manager.possibleanswers", "pk": 163, "fields": {"question": 18, "question_possible_answers": 3}}, {"model": "Test_manager.possibleanswers", "pk": 164, "fields": {"question": 18, "question_possible_answers": 4}}, {"model": "Test_manager.possibleanswers", "pk": 165, "fields": {"question": 18, "question_possible_answers": 5}}, {"model": "Test_manager.possibleanswers", "pk": 166, "fields": {"question": 18, "question_possible_answers": 6}}, {"model": "Test_manager.possibleanswers", "pk": 167, "fields": {"question": 18, "question_possible_answers": 7}}, {"model": "Test_manager.possibleanswers", "pk": 168, "fields": {"question": 18, "question_possible_answers": 8}}, {"model": "Test_manager.possibleanswers", "pk": 169, "fields": {"question": 18, "question_possible_answers": 9}}, {"model": "Test_manager.possibleanswers", "pk": 170, "fields": {"question": 18, "question_possible_answers": 10}}, {"model": "Test_manager.possibleanswers", "pk": 171, "fields": {"question": 18, "question_possible_answers": 11}}, {"model": "Test_manager.possibleanswers", "pk": 172, "fields": {"question": 18, "question_possible_answers": 12}}, {"model": "Test_manager.possibleanswers", "pk": 173, "fields": {"question": 18, "question_possible_answers": 13}}, {"model": "Test_manager.possibleanswers", "pk": 174, "fields": {"question": 18, "question_possible_answers": 14}}, {"model": "Test_manager.possibleanswers", "pk": 175, "fields": {"question": 18, "question_possible_answers": 15}}, {"model": "Test_manager.possibleanswers", "pk": 176, "fields": {"question": 18, "question_possible_answers": 16}}, {"model": "Test_manager.possibleanswers", "pk": 177, "fields": {"question": 19, "question_possible_answers": 1}}, {"model": "Test_manager.possibleanswers", "pk": 178, "fields": {"question": 19, "question_possible_answers": 2}}, {"model": "Test_manager.possibleanswers", "pk": 179, "fields": {"question": 19, "question_possible_answers": 3}}, {"model": "Test_manager.possibleanswers", "pk": 180, "fields": {"question": 19, "question_possible_answers": 4}}, {"model": "Test_manager.possibleanswers", "pk": 181, "fields": {"question": 19, "question_possible_answers": 5}}, {"model": "Test_manager.possibleanswers", "pk": 182, "fields": {"question": 19, "question_possible_answers": 6}}, {"model": "Test_manager.possibleanswers", "pk": 183, "fields": {"question": 19, "question_possible_answers": 7}}, {"model": "Test_manager.possibleanswers", "pk": 184, "fields": {"question": 19, "question_possible_answers": 8}}, {"model": "Test_manager.possibleanswers", "pk": 185, "fields": {"question": 19, "question_possible_answers": 9}}, {"model": "Test_manager.possibleanswers", "pk": 186, "fields": {"question": 19, "question_possible_answers": 10}}, {"model": "Test_manager.possibleanswers", "pk": 187, "fields": {"question": 19, "question_possible_answers": 11}}, {"model": "Test_manager.possibleanswers", "pk": 188, "fields": {"question": 19, "question_possible_answers": 12}}, {"model": "Test_manager.possibleanswers", "pk": 189, "fields": {"question": 19, "question_possible_answers": 13}}, {"model": "Test_manager.possibleanswers", "pk": 190, "fields": {"question": 19, "question_possible_answers": 14}}, {"model": "Test_manager.possibleanswers", "pk": 191, "fields": {"question": 19, "question_possible_answers": 15}}, {"model": "Test_manager.possibleanswers", "pk": 192, "fields": {"question": 19, "question_possible_answers": 16}}, {"model": "Test_manager.possibleanswers", "pk": 193, "fields": {"question": 20, "question_possible_answers": 1}}, {"model": "Test_manager.possibleanswers", "pk": 194, "fields": {"question": 20, "question_possible_answers": 2}}, {"model": "Test_manager.possibleanswers", "pk": 195, "fields": {"question": 20, "question_possible_answers": 3}}, {"model": "Test_manager.possibleanswers", "pk": 196, "fields": {"question": 20, "question_possible_answers": 4}}, {"model": "Test_manager.possibleanswers", "pk": 197, "fields": {"question": 20, "question_possible_answers": 5}}, {"model": "Test_manager.possibleanswers", "pk": 198, "fields": {"question": 20, "question_possible_answers": 6}}, {"model": "Test_manager.possibleanswers", "pk": 199, "fields": {"question": 20, "question_possible_answers": 7}}, {"model": "Test_manager.possibleanswers", "pk": 200, "fields": {"question": 20, "question_possible_answers": 8}}, {"model": "Test_manager.possibleanswers", "pk": 201, "fields": {"question": 20, "question_possible_answers": 9}}, {"model": "Test_manager.possibleanswers", "pk": 202, "fields": {"question": 20, "question_possible_answers": 10}}, {"model": "Test_manager.possibleanswers", "pk": 203, "fields": {"question": 20, "question_possible_answers": 11}}, {"model": "Test_manager.possibleanswers", "pk": 204, "fields": {"question": 20, "question_possible_answers": 12}}, {"model": "Test_manager.possibleanswers", "pk": 205, "fields": {"question": 20, "question_possible_answers": 13}}, {"model": "Test_manager.possibleanswers", "pk": 206, "fields": {"question": 20, "question_possible_answers": 14}}, {"model": "Test_manager.possibleanswers", "pk": 207, "fields": {"question": 20, "question_possible_answers": 15}}, {"model": "Test_manager.possibleanswers", "pk": 208, "fields": {"question": 20, "question_possible_answers": 16}}, {"model": "Test_manager.possibleanswers", "pk": 209, "fields": {"question": 21, "question_possible_answers": 1}}, {"model": "Test_manager.possibleanswers", "pk": 210, "fields": {"question": 21, "question_possible_answers": 2}}, {"model": "Test_manager.possibleanswers", "pk": 211, "fields": {"question": 21, "question_possible_answers": 3}}, {"model": "Test_manager.possibleanswers", "pk": 212, "fields": {"question": 21, "question_possible_answers": 4}}, {"model": "Test_manager.possibleanswers", "pk": 213, "fields": {"question": 21, "question_possible_answers": 5}}, {"model": "Test_manager.possibleanswers", "pk": 214, "fields": {"question": 21, "question_possible_answers": 6}}, {"model": "Test_manager.possibleanswers", "pk": 215, "fields": {"question": 21, "question_possible_answers": 7}}, {"model": "Test_manager.possibleanswers", "pk": 216, "fields": {"question": 21, "question_possible_answers": 8}}, {"model": "Test_manager.possibleanswers", "pk": 217, "fields": {"question": 21, "question_possible_answers": 9}}, {"model": "Test_manager.possibleanswers", "pk": 218, "fields": {"question": 21, "question_possible_answers": 10}}, {"model": "Test_manager.possibleanswers", "pk": 219, "fields": {"question": 21, "question_possible_answers": 11}}, {"model": "Test_manager.possibleanswers", "pk": 220, "fields": {"question": 21, "question_possible_answers": 12}}, {"model": "Test_manager.possibleanswers", "pk": 221, "fields": {"question": 21, "question_possible_answers": 13}}, {"model": "Test_manager.possibleanswers", "pk": 222, "fields": {"question": 21, "question_possible_answers": 14}}, {"model": "Test_manager.possibleanswers", "pk": 223, "fields": {"question": 21, "question_possible_answers": 15}}, {"model": "Test_manager.possibleanswers", "pk": 224, "fields": {"question": 21, "question_possible_answers": 16}}, {"model": "Test_manager.correctanswer", "pk": 1, "fields": {"question": 1, "question_correct_answers": 17}}, {"model": "Test_manager.correctanswer", "pk": 2, "fields": {"question": 2, "question_correct_answers": 18}}, {"model": "Test_manager.correctanswer", "pk": 3, "fields": {"question": 3, "question_correct_answers": 18}}, {"model": "Test_manager.correctanswer", "pk": 4, "fields": {"question": 4, "question_correct_answers": 18}}, {"model": "Test_manager.correctanswer", "pk": 5, "fields": {"question": 5, "question_correct_answers": 17}}, {"model": "Test_manager.correctanswer", "pk": 6, "fields": {"question": 6, "question_correct_answers": 18}}, {"model": "Test_manager.correctanswer", "pk": 7, "fields": {"question": 7, "question_correct_answers": 17}}, {"model": "Test_manager.correctanswer", "pk": 8, "fields": {"question": 8, "question_correct_answers": 17}}, {"model": "Test_manager.correctanswer", "pk": 9, "fields": {"question": 9, "question_correct_answers": 2}}, {"model": "Test_manager.correctanswer", "pk": 10, "fields": {"question": 9, "question_correct_answers": 13}}, {"model": "Test_manager.correctanswer", "pk": 11, "fields": {"question": 10, "question_correct_answers": 1}}, {"model": "Test_manager.correctanswer", "pk": 12, "fields": {"question": 10, "question_correct_answers": 11}}, {"model": "Test_manager.correctanswer", "pk": 13, "fields": {"question": 10, "question_correct_answers": 12}}, {"model": "Test_manager.correctanswer", "pk": 14, "fields": {"question": 10, "question_correct_answers": 15}}, {"model": "Test_manager.correctanswer", "pk": 15, "fields": {"question": 11, "question_correct_answers": 9}}, {"model": "Test_manager.correctanswer", "pk": 16, "fields": {"question": 11, "question_correct_answers": 14}}, {"model": "Test_manager.correctanswer", "pk": 17, "fields": {"question": 12, "question_correct_answers": 4}}, {"model": "Test_manager.correctanswer", "pk": 18, "fields": {"question": 13, "question_correct_answers": 9}}, {"model": "Test_manager.correctanswer", "pk": 19, "fields": {"question": 13, "question_correct_answers": 15}}, {"model": "Test_manager.correctanswer", "pk": 20, "fields": {"question": 14, "question_correct_answers": 4}}, {"model": "Test_manager.correctanswer", "pk": 21, "fields": {"question": 15, "question_correct_answers": 6}}, {"model": "Test_manager.correctanswer", "pk": 22, "fields": {"question": 15, "question_correct_answers": 16}}, {"model": "Test_manager.correctanswer", "pk": 23, "fields": {"question": 16, "question_correct_answers": 7}}, {"model": "Test_manager.correctanswer", "pk": 24, "fields": {"question": 17, "question_correct_answers": 9}}, {"model": "Test_manager.correctanswer", "pk": 25, "fields": {"question": 17, "question_correct_answers": 15}}, {"model": "Test_manager.correctanswer", "pk": 26, "fields": {"question": 18, "question_correct_answers": 1}}, {"model": "Test_manager.correctanswer", "pk": 27, "fields": {"question": 18, "question_correct_answers": 15}}, {"model": "Test_manager.correctanswer", "pk": 28, "fields": {"question": 19, "question_correct_answers": 9}}, {"model": "Test_manager.correctanswer", "pk": 29, "fields": {"question": 19, "question_correct_answers": 14}}, {"model": "Test_manager.correctanswer", "pk": 30, "fields": {"question": 20, "question_correct_answers": 2}}, {"model": "Test_manager.correctanswer", "pk": 31, "fields": {"question": 21, "question_correct_answers": 2}}, {"model": "User_manager.user", "pk": 1, "fields": {"password": "pbkdf2_sha256$390000$u2TsqpfT27jfGzXCfuiA9i$sjfgw4uvxKUVICOqwG9mxXpCLhVRlqLd5/4nxgd97Jo=", "last_login": "2023-02-15T23:48:07.693Z", "is_superuser": true, "username": "admin", "first_name": "", "last_name": "", "email": "admin@admin.pl", "is_staff": true, "is_active": true, "date_joined": "2023-02-15T23:33:54.468Z", "phone_number": null, "league": null, "slug": "admin-1676504034", "groups": [4], "user_permissions": []}}, {"model": "User_manager.user", "pk": 2, "fields": {"password": "pbkdf2_sha256$390000$oDzgLh13iHaOie7Husl2KF$k4BfjqAAqaI+vYIhDKeu2B5W2TiZqhquKarUEdKRQww=", "last_login": null, "is_superuser": false, "username": "sedzia@wp.pl", "first_name": "Zwykly", "last_name": "Sedzia", "email": "", "is_staff": false, "is_active": true, "date_joined": "2023-02-15T23:38:26.088Z", "phone_number": 123456789, "league": 1, "slug": "sedziawppl-1676504306", "groups": [1], "user_permissions": []}}, {"model": "User_manager.user", "pk": 3, "fields": {"password": "pbkdf2_sha256$390000$wYNB4OOBDrJmthlQKsKgPy$J4nPusA3BHcLgqCDOtGJnMVVw2T55FqjgQyq3nnvmIU=", "last_login": null, "is_superuser": false, "username": "szkolenie@op.pl", "first_name": "Komisja", "last_name": "szkoleniowa", "email": "", "is_staff": false, "is_active": true, "date_joined": "2023-02-15T23:47:30Z", "phone_number": 13245678, "league": 1, "slug": "szkolenieoppl-1676504850", "groups": [2], "user_permissions": []}}, {"model": "User_manager.user", "pk": 4, "fields": {"password": "pbkdf2_sha256$390000$N2kQgtpNaotIWDe02ug6Kb$qKR8UAMC39FAlBSxF1v2wMvjk/kCPdcnfOfeRLAtlK4=", "last_login": null, "is_superuser": false, "username": "organiser@op.pl", "first_name": "Organizator", "last_name": "Testow", "email": "", "is_staff": false, "is_active": true, "date_joined": "2023-02-15T23:47:57Z", "phone_number": 45678913, "league": 1, "slug": "organiseroppl-1676504877", "groups": [3], "user_permissions": []}}, {"model": "User_manager.league", "pk": 1, "fields": {"which_league": "IV liga", "slug": "iv-liga-1675858870"}}, {"model": "User_manager.league", "pk": 2, "fields": {"which_league": "Klasa okręgowa", "slug": "klasa-okregowa-1675858870"}}, {"model": "User_manager.league", "pk": 3, "fields": {"which_league": "Klasa A", "slug": "klasa-a-1675858870"}}, {"model": "User_manager.league", "pk": 4, "fields": {"which_league": "Klasa B", "slug": "klasa-b-1675858870"}}, {"model": "User_manager.league", "pk": 5, "fields": {"which_league": "Obserwator", "slug": "obserwator-1675858870"}}, {"model": "User_manager.league", "pk": 6, "fields": {"which_league": "Wszystkie", "slug": "wszystkie-1675858870"}}]